<?xml version="1.0" encoding="UTF-8"?>
<Meta>
    <Date>20.04.2016</Date>
    <Description short="Ignore strip list for SVD planes in 2016 VXD beam test">
        Crude initial list of bad strips
    </Description>
    <Author>Peter Kodys</Author>
</Meta>
<SVD>
    <layer n="3">
        <ladder n="1">
            <sensor n="1">
                <side side="u">
                    <!-- stripsFromTo fromStrip = "620" toStrip = "767"></stripsFromTo-->
                    <!-- Individual strips can be masked, too -->
                </side>
                <side side="v">
                </side>
            </sensor>
            <sensor n="2">
                <side side="u">
                    <!-- stripsFromTo fromStrip = "620" toStrip = "767"></stripsFromTo-->
                    <!-- Individual strips can be masked, too -->
                    <strip stripNo = "257"></strip>
                    <strip stripNo = "258"></strip>
                    <strip stripNo = "388"></strip>
                    <strip stripNo = "434"></strip>
                    <strip stripNo = "435"></strip>
                    <strip stripNo = "527"></strip>
                </side>
                <side side="v">
                    <strip stripNo = "484"></strip>
                    <strip stripNo = "485"></strip>
                    <strip stripNo = "511"></strip>
                    <strip stripNo = "522"></strip>
                    <strip stripNo = "523"></strip>
                    <strip stripNo = "540"></strip>
                    <strip stripNo = "541"></strip>
                </side>
            </sensor>
        </ladder>
    </layer>
    <layer n="4">
        <ladder n="1">
            <sensor n="1">
                <side side="u">
                    <!-- stripsFromTo fromStrip = "620" toStrip = "767"></stripsFromTo-->
                    <!-- Individual strips can be masked, too -->
                </side>
                <side side="v">
                </side>
            </sensor>
            <sensor n="2">
                <side side="u">
                    <!-- stripsFromTo fromStrip = "620" toStrip = "767"></stripsFromTo-->
                    <!-- Individual strips can be masked, too -->
                    <strip stripNo = "286"></strip>
                    <strip stripNo = "287"></strip>
                    <strip stripNo = "288"></strip>
                    <strip stripNo = "387"></strip>
                    <strip stripNo = "412"></strip>
                    <strip stripNo = "413"></strip>
                    <strip stripNo = "476"></strip>
                    <strip stripNo = "477"></strip>
                </side>
                <side side="v">
                    <strip stripNo = "79"></strip>
                    <strip stripNo = "100"></strip>
                    <strip stripNo = "108"></strip>
                </side>
            </sensor>
            <sensor n="3">
                <side side="u">
                    <!-- stripsFromTo fromStrip = "620" toStrip = "767"></stripsFromTo-->
                    <!-- Individual strips can be masked, too -->
                </side>
                <side side="v">
                </side>
            </sensor>
        </ladder>
    </layer>
    <layer n="5">
        <ladder n="1">
            <sensor n="1">
                <side side="u">
                    <!-- stripsFromTo fromStrip = "620" toStrip = "767"></stripsFromTo-->
                    <!-- Individual strips can be masked, too -->
                </side>
                <side side="v">
                </side>
            </sensor>
            <sensor n="2">
                <side side="u">
                    <!-- stripsFromTo fromStrip = "620" toStrip = "767"></stripsFromTo-->
                    <!-- Individual strips can be masked, too -->
                </side>
                <side side="v">
                </side>
            </sensor>
            <sensor n="3">
                <side side="u">
                    <!-- stripsFromTo fromStrip = "620" toStrip = "767"></stripsFromTo-->
                    <!-- Individual strips can be masked, too -->
                    <strip stripNo = "282"></strip>
                    <strip stripNo = "380"></strip>
                    <strip stripNo = "381"></strip>
                    <strip stripNo = "386"></strip>
                    <strip stripNo = "387"></strip>
                    <strip stripNo = "388"></strip>
                    <strip stripNo = "409"></strip>
                    <strip stripNo = "410"></strip>
                    <strip stripNo = "474"></strip>
                    <strip stripNo = "475"></strip>
                </side>
                <side side="v">
                    <strip stripNo = "239"></strip>
                    <strip stripNo = "240"></strip>
                    <strip stripNo = "262"></strip>
                    <strip stripNo = "270"></strip>
                    <strip stripNo = "271"></strip>
                    <strip stripNo = "272"></strip>
                    <strip stripNo = "279"></strip>
                </side>
            </sensor>
            <sensor n="4">
                <side side="u">
                    <!-- stripsFromTo fromStrip = "620" toStrip = "767"></stripsFromTo-->
                    <!-- Individual strips can be masked, too -->
                </side>
                <side side="v">
                </side>
            </sensor>
        </ladder>
    </layer>
    <layer n="6">
        <ladder n="1">
            <sensor n="1">
                <side side="u">
                    <!-- stripsFromTo fromStrip = "620" toStrip = "767"></stripsFromTo-->
                    <!-- Individual strips can be masked, too -->
                    <strip stripNo = "296"></strip>
                </side>
                <side side="v">
                </side>
            </sensor>
            <sensor n="2">
                <side side="u">
                    <!-- stripsFromTo fromStrip = "620" toStrip = "767"></stripsFromTo-->
                    <!-- Individual strips can be masked, too -->
                </side>
                <side side="v">
                </side>
            </sensor>
            <sensor n="3">
                <side side="u">
                    <!-- stripsFromTo fromStrip = "620" toStrip = "767"></stripsFromTo-->
                    <!-- Individual strips can be masked, too -->
                </side>
                <side side="v">
                </side>
            </sensor>
            <sensor n="4">
                <side side="u">
                    <!-- stripsFromTo fromStrip = "620" toStrip = "767"></stripsFromTo-->
                    <!-- Individual strips can be masked, too -->
                    <strip stripNo = "178"></strip>
                    <strip stripNo = "277"></strip>
                    <strip stripNo = "278"></strip>
                    <strip stripNo = "391"></strip>
                    <strip stripNo = "392"></strip>
                    <strip stripNo = "411"></strip>
                    <strip stripNo = "476"></strip>
                </side>
                <side side="v">
                    <strip stripNo = "458"></strip>
                    <strip stripNo = "459"></strip>
                    <strip stripNo = "483"></strip>
                    <strip stripNo = "484"></strip>
                    <strip stripNo = "492"></strip>
                    <strip stripNo = "501"></strip>
                    <strip stripNo = "502"></strip>
                </side>
            </sensor>
            <sensor n="5">
                <side side="u">
                    <!-- stripsFromTo fromStrip = "620" toStrip = "767"></stripsFromTo-->
                    <!-- Individual strips can be masked, too -->
                </side>
                <side side="v">
                </side>
            </sensor>
        </ladder>
    </layer>
</SVD>
