<?xml version="1.0" encoding="UTF-8"?>
<Meta>
	<Date>27/06/2016</Date>
	<Description short="List of known defects for SVD planes in 2016 TB">
		List of known strip defects, built using input from ladders groups, used to analyse 2016
        testbeam data.
	</Description>
	<Author>Giacomo Caria</Author>
</Meta>
<!-- Using u/v strip numbers: True.
     List of input files used to produce this mask is appended at end of file.
     List of defects included in this mask: 
	pinhole_dssd 
	metal_open_dssd 
	metal_short_dssd 
	pinhole_et 
	open_et 
	short_et -->
<SVD>
	<layer n="3">
		<ladder n="1">
			<sensor n="1">
				<side side="v">
					<strip stripNo = "764"></strip>
					<!--  defect1 = "pinhole_DSSD" defect2 = "Pinhole_ET" -->
					<strip stripNo = "763"></strip>
					<!--  defect1 = "pinhole_DSSD" defect2 = "Pinhole_ET" -->
					<strip stripNo = "760"></strip>
					<!--  defect1 = "pinhole_DSSD" defect2 = "Pinhole_ET" -->
				</side>
				<side side="u">
					<strip stripNo = "417"></strip>
					<!--  defect1 = "Short_ET" -->
					<strip stripNo = "416"></strip>
					<!--  defect1 = "Metal_Short_DSSD" defect2 = "Short_ET" -->
					<strip stripNo = "415"></strip>
					<!--  defect1 = "Metal_Short_DSSD" -->
					<strip stripNo = "411"></strip>
					<!--  defect1 = "Metal_Short_DSSD" defect2 = "Short_ET" -->
					<strip stripNo = "410"></strip>
					<!--  defect1 = "Metal_Short_DSSD" defect2 = "Short_ET" -->
					<strip stripNo = "409"></strip>
					<!--  defect1 = "Metal_Short_DSSD" defect2 = "Short_ET" -->
					<strip stripNo = "278"></strip>
					<!--  defect1 = "Pinhole_ET" -->
				</side>
			</sensor>
			<sensor n="2">
				<side side="v">
				</side>
				<side side="u">
				</side>
			</sensor>
		</ladder>
	</layer>
	<layer n="4">
		<ladder n="1">
			<sensor n="1">
				<side side="v">
					<strip stripNo = "308"></strip>
					<!--  defect1 = "pinhole_DSSD" defect2 = "Pinhole_ET" -->
				</side>
				<side side="u">
					<strip stripNo = "0"></strip>
					<!--  defect1 = "Open_ET" -->
					<strip stripNo = "113"></strip>
					<!--  defect1 = "pinhole_DSSD" defect2 = "Pinhole_ET" -->
					<strip stripNo = "149"></strip>
					<!--  defect1 = "pinhole_DSSD" defect2 = "Pinhole_ET" -->
					<strip stripNo = "194"></strip>
					<!--  defect1 = "Open_ET" -->
					<strip stripNo = "262"></strip>
					<!--  defect1 = "Short_ET" -->
					<strip stripNo = "263"></strip>
					<!--  defect1 = "Short_ET" -->
					<strip stripNo = "290"></strip>
					<!--  defect1 = "Short_ET" -->
					<strip stripNo = "291"></strip>
					<!--  defect1 = "Short_ET" -->
					<strip stripNo = "314"></strip>
					<!--  defect1 = "Short_ET" -->
					<strip stripNo = "315"></strip>
					<!--  defect1 = "Short_ET" -->
					<strip stripNo = "414"></strip>
					<!--  defect1 = "pinhole_DSSD" defect2 = "Pinhole_ET" -->
					<strip stripNo = "466"></strip>
					<!--  defect1 = "pinhole_DSSD" defect2 = "Pinhole_ET" -->
				</side>
			</sensor>
			<sensor n="2">
				<side side="v">
					<strip stripNo = "74"></strip>
					<!--  defect1 = "Open_ET" -->
					<strip stripNo = "126"></strip>
					<!--  defect1 = "Open_ET" -->
				</side>
				<side side="u">
					<strip stripNo = "754"></strip>
					<!--  defect1 = "Pinhole_ET" -->
					<strip stripNo = "356"></strip>
					<!--  defect1 = "metal_open_DSSD" -->
					<strip stripNo = "309"></strip>
					<!--  defect1 = "Short_ET" -->
					<strip stripNo = "308"></strip>
					<!--  defect1 = "Short_ET" -->
				</side>
			</sensor>
			<sensor n="3">
				<side side="v">
					<strip stripNo = "493"></strip>
					<!--  defect1 = "Pinhole_ET" -->
				</side>
				<side side="u">
					<strip stripNo = "757"></strip>
					<!--  defect1 = "pinhole_DSSD" defect2 = "Pinhole_ET" -->
				</side>
			</sensor>
		</ladder>
	</layer>
	<layer n="5">
		<ladder n="1">
			<sensor n="1">
			</sensor>
			<sensor n="2">
				<side side="v">
					<strip stripNo = "0"></strip>
					<!--  defect1 = "Open_ET" -->
					<strip stripNo = "3"></strip>
					<!--  defect1 = "Open_ET" -->
					<strip stripNo = "7"></strip>
					<!--  defect1 = "Pinhole_ET" -->
					<strip stripNo = "15"></strip>
					<!--  defect1 = "Pinhole_ET" -->
					<strip stripNo = "17"></strip>
					<!--  defect1 = "Pinhole_ET" -->
					<strip stripNo = "277"></strip>
					<!--  defect1 = "Pinhole_ET" -->
					<strip stripNo = "284"></strip>
					<!--  defect1 = "Pinhole_ET" -->
					<strip stripNo = "398"></strip>
					<!--  defect1 = "Open_ET" -->
					<strip stripNo = "426"></strip>
					<!--  defect1 = "Pinhole_ET" -->
					<strip stripNo = "442"></strip>
					<!--  defect1 = "Open_ET" -->
					<strip stripNo = "470"></strip>
					<!--  defect1 = "Open_ET" -->
				</side>
				<side side="u">
					<strip stripNo = "700"></strip>
					<!--  defect1 = "pinhole_DSSD" defect2 = "Pinhole_ET" -->
					<strip stripNo = "699"></strip>
					<!--  defect1 = "pinhole_DSSD" defect2 = "Pinhole_ET" -->
					<strip stripNo = "698"></strip>
					<!--  defect1 = "pinhole_DSSD" defect2 = "Pinhole_ET" -->
					<strip stripNo = "488"></strip>
					<!--  defect1 = "metal_open_DSSD" -->
					<strip stripNo = "369"></strip>
					<!--  defect1 = "metal_open_DSSD" -->
					<strip stripNo = "45"></strip>
					<!--  defect1 = "metal_open_DSSD" -->
					<strip stripNo = "17"></strip>
					<!--  defect1 = "pinhole_DSSD" defect2 = "Pinhole_ET" -->
				</side>
			</sensor>
			<sensor n="3">
				<side side="v">
					<strip stripNo = "0"></strip>
					<!--  defect1 = "Open_ET" -->
					<strip stripNo = "421"></strip>
					<!--  defect1 = "Short_ET" -->
					<strip stripNo = "423"></strip>
					<!--  defect1 = "Short_ET" -->
					<strip stripNo = "511"></strip>
					<!--  defect1 = "Open_ET" -->
				</side>
				<side side="u">
					<strip stripNo = "748"></strip>
					<!--  defect1 = "pinhole_DSSD" defect2 = "Pinhole_ET" -->
					<strip stripNo = "303"></strip>
					<!--  defect1 = "Open_ET" -->
					<strip stripNo = "137"></strip>
					<!--  defect1 = "Short_ET" -->
					<strip stripNo = "136"></strip>
					<!--  defect1 = "Short_ET" -->
					<strip stripNo = "49"></strip>
					<!--  defect1 = "Short_ET" -->
					<strip stripNo = "48"></strip>
					<!--  defect1 = "Short_ET" -->
					<strip stripNo = "2"></strip>
					<!--  defect1 = "pinhole_DSSD" defect2 = "Pinhole_ET" -->
					<strip stripNo = "1"></strip>
					<!--  defect1 = "pinhole_DSSD" defect2 = "Pinhole_ET" -->
				</side>
			</sensor>
			<sensor n="4">
				<side side="v">
					<strip stripNo = "278"></strip>
					<!--  defect1 = "Open_ET" -->
				</side>
				<side side="u">
				</side>
			</sensor>
		</ladder>
	</layer>
	<layer n="6">
		<ladder n="1">
			<sensor n="1">
				<side side="v">
				</side>
				<side side="u">
					<strip stripNo = "751"></strip>
					<!--  defect1 = "Open_ET" -->
				</side>
			</sensor>
			<sensor n="2">
				<side side="v">
				</side>
				<side side="u">
					<strip stripNo = "754"></strip>
					<!--  defect1 = "pinhole_DSSD" defect2 = "Pinhole_ET" -->
				</side>
			</sensor>
			<sensor n="3">
				<side side="v">
				</side>
				<side side="u">
					<strip stripNo = "767"></strip>
					<!--  defect1 = "Short_ET" -->
					<strip stripNo = "745"></strip>
					<!--  defect1 = "Open_ET" -->
					<strip stripNo = "1"></strip>
					<!--  defect1 = "Short_ET" -->
					<strip stripNo = "0"></strip>
					<!--  defect1 = "Short_ET" -->
				</side>
			</sensor>
			<sensor n="4">
				<side side="v">
					<strip stripNo = "15"></strip>
					<!--  defect1 = "Short_ET" -->
					<strip stripNo = "189"></strip>
					<!--  defect1 = "Short_ET" -->
				</side>
				<side side="u">
					<strip stripNo = "767"></strip>
					<!--  defect1 = "Short_ET" -->
					<strip stripNo = "766"></strip>
					<!--  defect1 = "Short_ET" -->
					<strip stripNo = "737"></strip>
					<!--  defect1 = "pinhole_DSSD" defect2 = "Pinhole_ET" -->
					<strip stripNo = "443"></strip>
					<!--  defect1 = "Short_ET" -->
					<strip stripNo = "442"></strip>
					<!--  defect1 = "Short_ET" -->
					<strip stripNo = "441"></strip>
					<!--  defect1 = "Short_ET" -->
					<strip stripNo = "415"></strip>
					<!--  defect1 = "Short_ET" -->
					<strip stripNo = "413"></strip>
					<!--  defect1 = "Short_ET" -->
					<strip stripNo = "410"></strip>
					<!--  defect1 = "Short_ET" -->
					<strip stripNo = "409"></strip>
					<!--  defect1 = "Short_ET" -->
					<strip stripNo = "407"></strip>
					<!--  defect1 = "Short_ET" -->
					<strip stripNo = "405"></strip>
					<!--  defect1 = "Short_ET" -->
					<strip stripNo = "402"></strip>
					<!--  defect1 = "Short_ET" -->
					<strip stripNo = "401"></strip>
					<!--  defect1 = "Short_ET" -->
					<strip stripNo = "399"></strip>
					<!--  defect1 = "Short_ET" -->
					<strip stripNo = "397"></strip>
					<!--  defect1 = "Short_ET" -->
					<strip stripNo = "394"></strip>
					<!--  defect1 = "Short_ET" -->
					<strip stripNo = "393"></strip>
					<!--  defect1 = "Short_ET" -->
					<strip stripNo = "391"></strip>
					<!--  defect1 = "Short_ET" -->
					<strip stripNo = "389"></strip>
					<!--  defect1 = "Short_ET" -->
					<strip stripNo = "386"></strip>
					<!--  defect1 = "Short_ET" -->
					<strip stripNo = "385"></strip>
					<!--  defect1 = "Short_ET" -->
					<strip stripNo = "0"></strip>
					<!--  defect1 = "Short_ET" -->
				</side>
			</sensor>
			<sensor n="5">
				<side side="v">
				</side>
				<side side="u">
					<strip stripNo = "759"></strip>
					<!--  defect1 = "metal_open_DSSD" defect2 = "Open_ET" -->
					<strip stripNo = "523"></strip>
					<!--  defect1 = "Pinhole_ET" -->
					<strip stripNo = "439"></strip>
					<!--  defect1 = "metal_open_DSSD" defect2 = "Open_ET" -->
					<strip stripNo = "267"></strip>
					<!--  defect1 = "metal_open_DSSD" defect2 = "Open_ET" -->
					<strip stripNo = "253"></strip>
					<!--  defect1 = "metal_open_DSSD" defect2 = "Open_ET" -->
				</side>
			</sensor>
		</ladder>
	</layer>
</SVD>
<!-- List of input files used to create this xml file: 
	./input_files/L3/L3.002_HPK_L3-15_fw_defects_Nside_20160419_1106.csv
	./input_files/L3/L3.002_HPK_L3-15_fw_defects_Pside_20160419_1106.csv
	./input_files/L3/L3.002_HPK_L3-08_bw_defects_Nside_20160419_1103.csv
	./input_files/L3/L3.002_HPK_L3-08_bw_defects_Pside_20160419_1103.csv
	./input_files/L4/L4.001_2965-12_Wedge_fw_defects_Nside_20160420_1228.csv
	./input_files/L4/L4.001_2965-12_Wedge_fw_defects_Pside_20160420_1228.csv
	./input_files/L4/L4.001_202012000042_-z_defects_Nside_20160419_1208.csv
	./input_files/L4/L4.001_202012000042_-z_defects_Pside_20160419_1208.csv
	./input_files/L4/L4.001_202012008170_bw_defects_Nside_20160419_1206.csv
	./input_files/L4/L4.001_202012008170_bw_defects_Pside_20160419_1206.csv
	File for layer 5, sensor 1 (fw), Nside, not found.
	File for layer 5, sensor 1 (fw), Pside, not found.
	./input_files/L5/L5.903_202012000060_ce_defects_Nside_20160417_2044_corrected_1.csv
	./input_files/L5/L5.903_202012000060_ce_defects_Pside_20160417_2044_corrected_3.csv
	./input_files/L5/L5.903_202012000054_-z_defects_Nside_20160417_2031_edited_3.csv
	./input_files/L5/L5.903_202012000054_-z_defects_Pside_20160417_2031_edited_3.csv
	./input_files/L5/L5.903_202012000084_bw_defects_Nside_20160417_2048.csv
	./input_files/L5/L5.903_202012000084_bw_defects_Pside_20160417_2048.csv
	./input_files/L6/L6.001_3084_15_Wedge_fw_defects_Nside_false_open_corrected.csv
	./input_files/L6/L6.001_3084_15_Wedge_fw_defects_Pside.csv
	./input_files/L6/L6.001_202012100065_+z_defects_Nside_false_open_corrected.csv
	./input_files/L6/L6.001_202012100065_+z_defects_Pside_false_short_corrected.csv
	./input_files/L6/L6.001_202012100072_ce_defects_Nside_false_open_corrected.csv
	./input_files/L6/L6.001_202012100072_ce_defects_Pside.csv
	./input_files/L6/L6.001_202012000083_-z_defects_Nside_false_open_corrected.csv
	./input_files/L6/L6.001_202012000083_-z_defects_Pside.csv
	./input_files/L6/L6.001_202012005097_bw_defects_Nside.csv
	./input_files/L6/L6.001_202012005097_bw_defects_Pside.csv -->
