<?xml version="1.0" encoding="UTF-8"?>

<CalPulseShape descr="unnormalized shape of the double calibration pulse">
  <sampleValues>
    0.54737 0.383567 0.166943 0.135527 0.180095 0.292344 0.191882 -0.113186
    -0.623617 -0.886863 -0.0322872 4.52087 16.2418 45.1288 94.5699 180.815
    288.428 428.46 552.518 655.081 701.619 702.204 652.734 537.758
    315.245 65.1362 -87.9718 -120.345 -87.4894 -34.317 -9.74887 -30.5014
    -86.1014 -142.684 -174.037 -183.516 -175.488 -159.858 -148.749 -146.509
    -152.624 -160.503 -164.514 -164.842 -163.095 -161.467 -160.833 -160.424
    -159.36 -156.936 -153.847 -150.804 -149.381 -149.673 -151.197 -152.692
    -152.848 -151.179 -148.34 -144.742 -141.735 -138.879 -136.637 -134.1
    -131.821 -129.357 -127.478 -125.3 -122.581 -116.552 -105.227 -80.8553
    -40.6558 29.7811 122.732 247.043 375.24 501.037 590.861 644.973
    639.492 571.794 426.478 246.597 61.5955 -79.6131 -148.597 -146.088
    -110.872 -73.9603 -65.1349 -83.4608 -114.314 -141.794 -158.926 -172.913
    -187.711 -208.39 -229.56 -246.589 -250.765 -241.538 -225.802 -211.777
    -209.26 -216.781 -227.112 -232.826 -229.414 -218.224 -206.982 -201.221
    -204.904 -214.675 -223.179 -225.512 -220.134 -208.806 -197.89 -189.508
    -186.522 -185.624 -184.256 -180.223 -174.918 -169.212 -165.565 -163.032
    -161.189 -158.196 -154.374 -149.33 -144.91 -140.467 -137.104 -133.737
    -131.461 -130.123 -130.316 -131.33 -132.278 -131.799 -129.54 -124.823
    -118.658 -109.752 -100.032 -88.1338 -76.255 -61.5043 -46.1626 -29.9987
    -21.0392 -24.1317 -40.9478 -66.4106 -87.1918 -97.0422 -93.09 -80.5838
    -68.1355 -59.9169 -59.4878 -63.263 -67.3309 -68.3801 -65.9523 -61.6487
    -58.5522 -57.7912 -59.7415 -62.835 -64.8542 -64.4543 -61.2963 -55.8905
    -50.4526 -45.2634 -42.0674 -39.4631 -37.6348 -35.6168 -33.588 -31.3105
    -29.3907 -27.542 -25.9053 -24.0517 -21.9769 -19.2034 -16.3061 -13.1031
    -10.5338 -8.32274 -6.9565 -5.54801 -4.33816 -2.73562 -1.29636 0.385735
  </sampleValues>
  <tailTimeConstant unit="ns"> 10.0 </tailTimeConstant> 
  <noiseBandwidth descr="given as second order low pass filter">
    <pole1 descr="MHz"> 140.0 </pole1>
    <pole2 descr="MHz"> 520.0 </pole2>
  </noiseBandwidth>
</CalPulseShape>
