<?xml version="1.0" encoding="UTF-8"?>
<ParamSet type="SVD">
	<Name>SVD</Name>
	<Description>The key component of the tracking system</Description>
	<Version>0</Version>
	<Creator>SVDBelleII</Creator>
	<Content xmlns:xi="http://www.w3.org/2001/XInclude">
		<Rotation desc="Rotation of the hole PXD detector (should be the same as beampipe)" unit="mrad">0.0</Rotation>
		<OffsetZ desc="The offset of the whole PXD in z with respect to the IP (should be the same as beampipe)" unit="mm">0.0</OffsetZ>		
		<Layers>
			<Layer id="3">
				<Phi0 desc="The starting angle of the layer in the r-phi plane" unit="deg">12.2</Phi0>
				<Radius desc="Radius of the layer" unit="mm">38.0</Radius>
				<OffsetY desc="The offset of the center of the ladder in y direction (Wind Mill structure)" unit="mm">-5.0</OffsetY>
				<OffsetZ desc="The offset of the center of the ladder in z direction" unit="mm">33.7</OffsetZ>
				<NumberOfLadders desc="Number of ladders in this layer">8</NumberOfLadders>
				<Ladder desc="The silicon modules the detector is made of">
            <xi:include href="SVDLadderBelleII.xml" xpointer="xpointer(/*/*)"/>
          <Theta desc="The tilt angle of the layer with respect to the z axis" unit="deg">0.0</Theta>
					<Length desc="The over all length of the ladder" unit="mm">236.4</Length>
					<NumberOfSensors>2</NumberOfSensors>
					<NumberOfSlantedSensors>0</NumberOfSlantedSensors>
					<Sensor>
					
                <Thickness desc="The over all thickness of the sensor" unit="mm">1</Thickness>
               <Length desc="The over all width of the sensor" unit="mm">124.880</Length>
               <Width desc="The overall length of the sensor" unit="mm">38.4</Width>
            	
    				   <MaterialSensor>Silicon</MaterialSensor>
                  <LengthActive desc="The over all length of the sensor" unit="mm">115.2</LengthActive>
                  <ThicknessActive desc="Thickness of the sensors" unit="um">300</ThicknessActive>
						<WidthActive desc="The over all width of the sensor" unit="mm">38.4</WidthActive>
						<PadSizeRPhi desc="pixel size or strip size" unit="um">25</PadSizeRPhi>
						<PadSizeZ desc="pixel size or strip size" unit="um">75</PadSizeZ>
					</Sensor>
				</Ladder>
			</Layer>
			
			<Layer id="4">
				<Phi0 desc="The starting angle of the layer in the r-phi plane" unit="deg">5.0</Phi0>
				<Radius desc="Radius of the layer" unit="mm">80.0</Radius>
				<Radius2 desc="Radius of the layer for slanted sensors" unit="mm">66</Radius2>
				<OffsetY desc="The offset of the center of the ladder in y direction (Wind Mill structure)" unit="mm">-8.0</OffsetY>
				<OffsetZ desc="The offset of the center of the ladder in z direction" unit="mm">-37.3</OffsetZ>
				<OffsetZ2 desc="The offset of the center of the layer in z direction for slanted sensors" unit="mm">142.0</OffsetZ2>
				<NumberOfLadders desc="Number of ladders in this layer">10</NumberOfLadders>
				<Ladder desc="The silicon modules the detector is made of">
            <xi:include href="SVDLadderBelleII.xml" xpointer="xpointer(/*/*)"/>
          <Theta desc="The tilt angle of the slanted sensor with respect to the z axis" unit="deg">13.4</Theta>
					<Length desc="The over all length of the barrel part of ladder" unit="mm">236.4</Length>
					 <Length2 desc="The over all length of the slanted part of the ladder" unit="mm">117.2</Length2>
					<NumberOfSensors>2</NumberOfSensors>
					<NumberOfSlantedSensors desc="The number of slanted sensors in forward direction">1</NumberOfSlantedSensors>
					<Sensor>
						   <xi:include href="SVDSensorBelleII.xml" xpointer="xpointer(/*/*)"/>
					</Sensor>
						<SlantedSensor>
						   <xi:include href="SVDSensorSlantedBelleII.xml" xpointer="xpointer(/*/*)"/>
					</SlantedSensor>
				</Ladder>
			</Layer>

			<Layer id="5">
				<Phi0 desc="The starting angle of the layer in the r-phi plane" unit="deg">14.4</Phi0>

				<Radius desc="Radius of the layer" unit="mm">115.0</Radius>
    			<Radius2 desc="Radius of slanted part of the ladder" unit="mm">95.5</Radius2>
				<OffsetY desc="The offset of the center of the ladder in y direction (Wind Mill structure)" unit="mm">-8.0</OffsetY>
				<OffsetZ desc="The offset of the center of the barrel part sensor of the layer in z direction" unit="mm">-28.2</OffsetZ>
			<OffsetZ2 desc="The offset of the center of the slanted sensors of the layer in z direction" unit="mm">211.2</OffsetZ2>
				<NumberOfLadders desc="Number of ladders in this layer">14</NumberOfLadders>
				<Ladder desc="The silicon modules the detector is made of">
            <xi:include href="SVDLadderBelleII.xml" xpointer="xpointer(/*/*)"/>
          <Theta desc="The tilt angle of the slanted sensors with respect to the z axis" unit="deg">19.4</Theta>
					<Length desc="The over all length of the barrel part of the ladder" unit="mm">355.6</Length>
				<Length2 desc="The over all length of the slanted part of the ladder" unit="mm">117.2</Length2>
					<NumberOfSensors>3</NumberOfSensors>
					<NumberOfSlantedSensors>1</NumberOfSlantedSensors>
					<Sensor>
						   <xi:include href="SVDSensorBelleII.xml" xpointer="xpointer(/*/*)"/>
					</Sensor>
						<SlantedSensor>
						   <xi:include href="SVDSensorSlantedBelleII.xml" xpointer="xpointer(/*/*)"/>
					</SlantedSensor>
			</Ladder>
			</Layer>
				
		
			<Layer id="6">
				<Phi0 desc="The starting angle of the layer in the r-phi plane" unit="deg">5.3</Phi0>
				<Radius desc="Radius of the layer" unit="mm">140</Radius>
   			<Radius2 desc="Radius of slanted part of the ladder" unit="mm">114.0</Radius2>
				<OffsetY desc="The offset of the center of the ladder in y direction (Wind Mill structure)" unit="mm">-8.0</OffsetY>
				<OffsetZ desc="The offset of the center of the ladder in z direction" unit="mm">-19.1</OffsetZ>
    			<OffsetZ2 desc="The offset of the center of the slanted sensors of the layer in z direction" unit="mm">280.4</OffsetZ2>
				<NumberOfLadders desc="Number of ladders in this layer">17</NumberOfLadders>
				<Ladder desc="The silicon modules the detector is made of">
            <xi:include href="SVDLadderBelleII.xml" xpointer="xpointer(/*/*)"/>
								<Theta desc="The tilt angle of the slanted sensors with respect to the z axis" unit="deg">23.9</Theta>
					<Length desc="The over all length of the ladder" unit="mm">474.8</Length>
					<Length2 desc="The over all length of the slanted part of the ladder" unit="mm">117.2</Length2>
					<NumberOfSensors>4</NumberOfSensors>
					<NumberOfSlantedSensors>1</NumberOfSlantedSensors>
					<Sensor>
						   <xi:include href="SVDSensorBelleII.xml" xpointer="xpointer(/*/*)"/>
					</Sensor>
						<SlantedSensor>
						   <xi:include href="SVDSensorSlantedBelleII.xml" xpointer="xpointer(/*/*)"/>
					</SlantedSensor>
				</Ladder>
			</Layer>
		</Layers>
	</Content>
</ParamSet>

